docker_composer/__init__.py
docker_composer/base.py
docker_composer/py.typed
docker_composer/_utils/__init__.py
docker_composer/_utils/argument.py
docker_composer/_utils/generate_class.py
docker_composer/runner/__init__.py
docker_composer/runner/root.py
docker_composer/runner/cmd/attach.py
docker_composer/runner/cmd/build.py
docker_composer/runner/cmd/config.py
docker_composer/runner/cmd/cp.py
docker_composer/runner/cmd/create.py
docker_composer/runner/cmd/down.py
docker_composer/runner/cmd/events.py
docker_composer/runner/cmd/exec.py
docker_composer/runner/cmd/images.py
docker_composer/runner/cmd/kill.py
docker_composer/runner/cmd/logs.py
docker_composer/runner/cmd/ls.py
docker_composer/runner/cmd/pause.py
docker_composer/runner/cmd/port.py
docker_composer/runner/cmd/ps.py
docker_composer/runner/cmd/pull.py
docker_composer/runner/cmd/push.py
docker_composer/runner/cmd/restart.py
docker_composer/runner/cmd/rm.py
docker_composer/runner/cmd/run.py
docker_composer/runner/cmd/scale.py
docker_composer/runner/cmd/start.py
docker_composer/runner/cmd/stats.py
docker_composer/runner/cmd/stop.py
docker_composer/runner/cmd/top.py
docker_composer/runner/cmd/unpause.py
docker_composer/runner/cmd/up.py
docker_composer/runner/cmd/version.py
docker_composer/runner/cmd/wait.py
docker_composer/runner/cmd/watch.py
docker_composer-2.79.7.dist-info/METADATA
docker_composer-2.79.7.dist-info/WHEEL
docker_composer-2.79.7.dist-info/licenses/LICENSE.txt
docker_composer-2.79.7.dist-info/RECORD
