Metadata-Version: 2.4
Name: docker-composer
Version: 2.79.7
Summary: Use docker-compose (V2) from within Python
Project-URL: Homepage, https://github.com/schollm/docker-composer
Project-URL: Repository, https://github.com/schollm/docker-composer
Author-email: Micha <schollm-git@gmx.com>
License-Expression: Apache-2.0
License-File: LICENSE.txt
Classifier: Development Status :: 5 - Production/Stable
Classifier: Intended Audience :: Developers
Classifier: Intended Audience :: System Administrators
Classifier: License :: OSI Approved :: Apache Software License
Classifier: Operating System :: OS Independent
Classifier: Programming Language :: Python :: 3
Classifier: Topic :: Software Development :: Build Tools
Classifier: Topic :: Software Development :: Libraries :: Application Frameworks
Requires-Python: <4.0,>=3.9
Requires-Dist: attrs>=20.3.0
Requires-Dist: loguru>=0.5.3
Requires-Dist: ruff>=0.11.10
